pyrostates/__init__.py
pyrostates/global_state_machine.py
pyrostates/state.py
pyrostates/state_group.py
pyrostates/state_machine.py
Pyrostates-1.0.1.dist-info/LICENSE
Pyrostates-1.0.1.dist-info/METADATA
Pyrostates-1.0.1.dist-info/WHEEL
Pyrostates-1.0.1.dist-info/top_level.txt
Pyrostates-1.0.1.dist-info/RECORD
