Metadata-Version: 2.2
Name: Pyrostates
Version: 1.0.1
Summary: A state handling extension for Pyrogram
Author-email: Sajjad <sajjadalipour2006@gmail.com>
License: Copyright (c) 2024-present SajjadAlipour2006
Project-URL: Homepage, https://github.com/SajjadAlipour2006/Pyrostates
Project-URL: Tracker, https://github.com/SajjadAlipour2006/Pyrostates/issues
Keywords: python,bot,telegram,pyrogram
Classifier: License :: OSI Approved :: MIT License
License-File: LICENSE
